{
 "homesss": [
  {
    "url": "/images/home/img1.jpg",
    "alt": "Welcome to our experience",
    "type": "image"
  },
  {
    "url": "/images/home/img2.jpg",
    "alt": "Discover something amazing",
    "type": "image"
  },
  {
    "url": "/images/home/img3.jpg",
    "alt": "Start your journey",
    "type": "image"
  },
  {
    "url": "/images/home/img4.jpg",
    "alt": "Explore more moments",
    "type": "image"
  },
  {
    "url": "/images/home/img5.jpg",
    "alt": "Capture the vibe",
    "type": "image"
  },
  {
    "url": "/images/home/img6.jpg",
    "alt": "Feel the connection",
    "type": "image"
  },
  {
    "url": "/images/home/img7.jpg",
    "alt": "Uncover hidden beauty",
    "type": "image"
  },
  {
    "url": "/images/home/img8.jpg",
    "alt": "Moments to remember",
    "type": "image"
  },
  {
    "url": "/images/home/img9.jpg",
    "alt": "The journey continues",
    "type": "image"
  },
  {
    "url": "/images/home/img10.jpg",
    "alt": "Experience the adventure",
    "type": "image"
  },
  {
    "url": "/images/home/img11.jpg",
    "alt": "Experience the adventure",
    "type": "image"
  }
],

"home": [
  {
    "url": "/images/home/image1.jpg",
    "alt": "Welcome to our experience",
    "type": "image"
  },
  {
    "url": "/images/home/image1.jpg",
    "alt": "Discover something amazing",
    "type": "image"
  }
  
],
  "next": [
    {
      "url": "/images/next/image1.jpg",
      "alt": "Try something new",
      "type": "image"
    },
    {
      "url": "/images/next/image2.jpg",
      "alt": "Explore further",
      "type": "image"
    },
    {
      "url": "/images/next/image3.jpg",
      "alt": "Continue your journey",
      "type": "image"
    }
  ],
 "attractions": [
  {
    "url": "/images/attractions/img1.jpg",
    "alt": "Attraction 1",
    "type": "image"
  },
  {
    "url": "/images/attractions/img2.jpg",
    "alt": "Attraction 2",
    "type": "image"
  },
  {
    "url": "/images/attractions/img3.jpg",
    "alt": "Attraction 3",
    "type": "image"
  },
  {
    "url": "/images/attractions/img4.jpg",
    "alt": "Attraction 4",
    "type": "image"
  },
  {
    "url": "/images/attractions/img5.jpg",
    "alt": "Attraction 5",
    "type": "image"
  },
  {
    "url": "/images/attractions/img6.jpg",
    "alt": "Attraction 6",
    "type": "image"
  },
  {
    "url": "/images/attractions/img7.jpg",
    "alt": "Attraction 7",
    "type": "image"
  },
  {
    "url": "/images/attractions/img8.jpg",
    "alt": "Attraction 8",
    "type": "image"
  },
  {
    "url": "/images/attractions/img9.jpg",
    "alt": "Attraction 9",
    "type": "image"
  },
  {
    "url": "/images/attractions/img10.jpg",
    "alt": "Attraction 10",
    "type": "image"
  },
  {
    "url": "/images/attractions/img11.jpg",
    "alt": "Attraction 11",
    "type": "image"
  },
  {
    "url": "/images/attractions/img12.jpg",
    "alt": "Attraction 12",
    "type": "image"
  },
  {
    "url": "/images/attractions/img13.jpg",
    "alt": "Attraction 13",
    "type": "image"
  },
  {
    "url": "/images/attractions/img14.jpg",
    "alt": "Attraction 14",
    "type": "image"
  },
  {
    "url": "/images/attractions/img15.jpg",
    "alt": "Attraction 15",
    "type": "image"
  },
  {
    "url": "/images/attractions/img16.jpg",
    "alt": "Attraction 16",
    "type": "image"
  },
  {
    "url": "/images/attractions/img17.jpg",
    "alt": "Attraction 17",
    "type": "image"
  },
  {
    "url": "/images/attractions/img18.jpg",
    "alt": "Attraction 18",
    "type": "image"
  },
  {
    "url": "/images/attractions/img19.jpg",
    "alt": "Attraction 19",
    "type": "image"
  },
  {
    "url": "/images/attractions/img20.jpg",
    "alt": "Attraction 20",
    "type": "image"
  },
  {
    "url": "/images/attractions/img21.jpg",
    "alt": "Attraction 21",
    "type": "image"
  },
  {
    "url": "/images/attractions/img22.jpg",
    "alt": "Attraction 22",
    "type": "image"
  },
  {
    "url": "/images/attractions/img23.jpg",
    "alt": "Attraction 23",
    "type": "image"
  },
  {
    "url": "/images/attractions/img24.jpg",
    "alt": "Attraction 24",
    "type": "image"
  },
  {
    "url": "/images/attractions/img25.jpg",
    "alt": "Attraction 25",
    "type": "image"
  },
  {
    "url": "/images/attractions/img26.jpg",
    "alt": "Attraction 26",
    "type": "image"
  },
  {
    "url": "/images/attractions/img27.jpg",
    "alt": "Attraction 27",
    "type": "image"
  },
  {
    "url": "/images/attractions/img28.jpg",
    "alt": "Attraction 28",
    "type": "image"
  },
  {
    "url": "/images/attractions/img29.jpg",
    "alt": "Attraction 29",
    "type": "image"
  },
  {
    "url": "/images/attractions/img30.jpg",
    "alt": "Attraction 30",
    "type": "image"
  },
  {
    "url": "/images/attractions/img31.jpg",
    "alt": "Attraction 31",
    "type": "image"
  },
  {
    "url": "/images/attractions/img32.jpg",
    "alt": "Attraction 32",
    "type": "image"
  },
  {
    "url": "/images/attractions/img33.jpg",
    "alt": "Attraction 33",
    "type": "image"
  },
  {
    "url": "/images/attractions/img34.jpg",
    "alt": "Attraction 34",
    "type": "image"
  },
  {
    "url": "/images/attractions/img35.jpg",
    "alt": "Attraction 35",
    "type": "image"
  },
  {
    "url": "/images/attractions/img36.jpg",
    "alt": "Attraction 36",
    "type": "image"
  },
  {
    "url": "/images/attractions/img37.jpg",
    "alt": "Attraction 37",
    "type": "image"
  },
  {
    "url": "/images/attractions/img38.jpg",
    "alt": "Attraction 38",
    "type": "image"
  },
  {
    "url": "/images/attractions/img39.jpg",
    "alt": "Attraction 39",
    "type": "image"
  },
  {
    "url": "/images/attractions/img40.jpg",
    "alt": "Attraction 40",
    "type": "image"
  },
  {
    "url": "/images/attractions/img41.jpg",
    "alt": "Attraction 41",
    "type": "image"
  },
  {
    "url": "/images/attractions/img42.jpg",
    "alt": "Attraction 42",
    "type": "image"
  },
  {
    "url": "/images/attractions/img43.jpg",
    "alt": "Attraction 43",
    "type": "image"
  },
  {
    "url": "/images/attractions/img44.jpg",
    "alt": "Attraction 44",
    "type": "image"
  },
  {
    "url": "/images/attractions/img45.jpg",
    "alt": "Attraction 45",
    "type": "image"
  },
  {
    "url": "/images/attractions/img46.jpg",
    "alt": "Attraction 46",
    "type": "image"
  }
],
  "store": [
    {
      "url": "/images/attractions/img1.jpg",
      "alt": "Attraction 1",
      "type": "image"
    },
    {
      "url": "/images/attractions/img2.jpg",
      "alt": "Attraction 2",
      "type": "image"
    },
    {
      "url": "/images/attractions/img3.jpg",
      "alt": "Attraction 3",
      "type": "image"
    },
    {
      "url": "/images/attractions/img4.jpg",
      "alt": "Attraction 4",
      "type": "image"
    },
    {
      "url": "/images/attractions/img5.jpg",
      "alt": "Attraction 5",
      "type": "image"
    },
    {
      "url": "/images/attractions/img6.jpg",
      "alt": "Attraction 6",
      "type": "image"
    },
    {
      "url": "/images/attractions/img7.jpg",
      "alt": "Attraction 7",
      "type": "image"
    },
    {
      "url": "/images/attractions/img8.jpg",
      "alt": "Attraction 8",
      "type": "image"
    },
    {
      "url": "/images/attractions/img9.jpg",
      "alt": "Attraction 9",
      "type": "image"
    },
    {
      "url": "/images/attractions/img10.jpg",
      "alt": "Attraction 10",
      "type": "image"
    },
    {
      "url": "/images/attractions/img11.jpg",
      "alt": "Attraction 11",
      "type": "image"
    },
    {
      "url": "/images/attractions/img12.jpg",
      "alt": "Attraction 12",
      "type": "image"
    },
    {
      "url": "/images/attractions/img13.jpg",
      "alt": "Attraction 13",
      "type": "image"
    },
    {
      "url": "/images/attractions/img14.jpg",
      "alt": "Attraction 14",
      "type": "image"
    },
    {
      "url": "/images/attractions/img15.jpg",
      "alt": "Attraction 15",
      "type": "image"
    },
    {
      "url": "/images/attractions/img16.jpg",
      "alt": "Attraction 16",
      "type": "image"
    },
    {
      "url": "/images/attractions/img17.jpg",
      "alt": "Attraction 17",
      "type": "image"
    },
    {
      "url": "/images/attractions/img18.jpg",
      "alt": "Attraction 18",
      "type": "image"
    },
    {
      "url": "/images/attractions/img19.jpg",
      "alt": "Attraction 19",
      "type": "image"
    },
    {
      "url": "/images/attractions/img20.jpg",
      "alt": "Attraction 20",
      "type": "image"
    },
    {
      "url": "/images/attractions/img21.jpg",
      "alt": "Attraction 21",
      "type": "image"
    },
    {
      "url": "/images/attractions/img22.jpg",
      "alt": "Attraction 22",
      "type": "image"
    },
    {
      "url": "/images/attractions/img23.jpg",
      "alt": "Attraction 23",
      "type": "image"
    },
    {
      "url": "/images/attractions/img24.jpg",
      "alt": "Attraction 24",
      "type": "image"
    },
    {
      "url": "/images/attractions/img25.jpg",
      "alt": "Attraction 25",
      "type": "image"
    },
    {
      "url": "/images/attractions/img26.jpg",
      "alt": "Attraction 26",
      "type": "image"
    },
    {
      "url": "/images/attractions/img27.jpg",
      "alt": "Attraction 27",
      "type": "image"
    },
    {
      "url": "/images/attractions/img28.jpg",
      "alt": "Attraction 28",
      "type": "image"
    },
    {
      "url": "/images/attractions/img29.jpg",
      "alt": "Attraction 29",
      "type": "image"
    },
    {
      "url": "/images/attractions/img30.jpg",
      "alt": "Attraction 30",
      "type": "image"
    },
    {
      "url": "/images/attractions/img31.jpg",
      "alt": "Attraction 31",
      "type": "image"
    },
    {
      "url": "/images/attractions/img32.jpg",
      "alt": "Attraction 32",
      "type": "image"
    },
    {
      "url": "/images/attractions/img33.jpg",
      "alt": "Attraction 33",
      "type": "image"
    },
    {
      "url": "/images/attractions/img34.jpg",
      "alt": "Attraction 34",
      "type": "image"
    },
    {
      "url": "/images/attractions/img35.jpg",
      "alt": "Attraction 35",
      "type": "image"
    },
    {
      "url": "/images/attractions/img36.jpg",
      "alt": "Attraction 36",
      "type": "image"
    },
    {
      "url": "/images/attractions/img37.jpg",
      "alt": "Attraction 37",
      "type": "image"
    },
    {
      "url": "/images/attractions/img38.jpg",
      "alt": "Attraction 38",
      "type": "image"
    },
    {
      "url": "/images/attractions/img39.jpg",
      "alt": "Attraction 39",
      "type": "image"
    },
    {
      "url": "/images/attractions/img40.jpg",
      "alt": "Attraction 40",
      "type": "image"
    },
    {
      "url": "/images/attractions/img41.jpg",
      "alt": "Attraction 41",
      "type": "image"
    },
    {
      "url": "/images/attractions/img42.jpg",
      "alt": "Attraction 42",
      "type": "image"
    },
    {
      "url": "/images/attractions/img43.jpg",
      "alt": "Attraction 43",
      "type": "image"
    },
    {
      "url": "/images/attractions/img44.jpg",
      "alt": "Attraction 44",
      "type": "image"
    },
    {
      "url": "/images/attractions/img45.jpg",
      "alt": "Attraction 45",
      "type": "image"
    },
    {
      "url": "/images/attractions/img46.jpg",
      "alt": "Attraction 46",
      "type": "image"
    }
  ],
  "story": [
    {
      "url": "/videos/story/video1.mp4",
      "alt": "Our story video 1",
      "type": "video"
    },
    {
      "url": "/videos/story/video2.mp4",
      "alt": "Our story video 2",
      "type": "video"
    },
    {
      "url": "/videos/story/video3.mp4",
      "alt": "Our story video 3",
      "type": "video"
    }
  ],
  "thankyou": [
    {
      "url": "/images/thankyou/image1.jpg",
      "alt": "Thank you for your interest",
      "type": "image"
    },
    {
      "url": "/images/thankyou/image2.jpg",
      "alt": "We appreciate your time",
      "type": "image"
    },
    {
      "url": "/images/thankyou/image3.jpg",
      "alt": "Looking forward to connecting",
      "type": "image"
    },
    {
      "url": "/images/thankyou/image4.jpg",
      "alt": "Your meeting is scheduled",
      "type": "image"
    },
    {
      "url": "/images/thankyou/image5.jpg",
      "alt": "We'll be in touch soon",
      "type": "image"
    }
  ]
}
